pyBaseApp/__init__.py
pyBaseApp/configuration.py
pyBaseApp/error.py
pyBaseApp/settings.py
tests/__init__.py
tests/unit/__init__.py
tests/unit/test_configuration.py
pyBaseApp-1.2.dist-info/LICENSE
pyBaseApp-1.2.dist-info/METADATA
pyBaseApp-1.2.dist-info/WHEEL
pyBaseApp-1.2.dist-info/top_level.txt
pyBaseApp-1.2.dist-info/RECORD
