Metadata-Version: 2.1
Name: pyBaseApp
Version: 1.2
Summary: Standard app configuration and packaging
Home-page: https://github.com/20centcroak/pyBaseApp
Author: 20centCroak
Author-email: 
License: UNKNOWN
Platform: UNKNOWN
Classifier: Programming Language :: Python :: 3
Classifier: License :: OSI Approved :: MIT License
Classifier: Operating System :: OS Independent
Requires-Python: >=3.6
Requires-Dist: PyYAML
